TMPPy-0.1.3.data/data/include/tmppy/tmppy.h
TMPPy-0.1.3.dist-info/DESCRIPTION.rst
TMPPy-0.1.3.dist-info/METADATA
TMPPy-0.1.3.dist-info/RECORD
TMPPy-0.1.3.dist-info/WHEEL
TMPPy-0.1.3.dist-info/entry_points.txt
TMPPy-0.1.3.dist-info/metadata.json
TMPPy-0.1.3.dist-info/top_level.txt
_py2tmp/__init__.py
_py2tmp/ast2highir.py
_py2tmp/errors.py
_py2tmp/highir.py
_py2tmp/highir2ir.py
_py2tmp/ir.py
_py2tmp/ir2lowir.py
_py2tmp/lowir.py
_py2tmp/lowir2cpp.py
_py2tmp/main.py
_py2tmp/utils.py
_py2tmp/testing/__init__.py
_py2tmp/testing/utils.py
_tmppy/__init__.py
_tmppy/lists.py
_tmppy/type.py
py2tmp/__init__.py
py2tmp/testing/__init__.py
tmppy/__init__.py
