Metadata-Version: 2.0
Name: TMPPy
Version: 0.1.3
Summary: A subset of Python that can be compiled to C++ meta-functions using the py2tmp compiler
Home-page: https://github.com/google/tmppy
Author: Marco Poletti
Author-email: poletti.marco@gmail.com
License: Apache 2.0
Keywords: C++ metaprogramming compiler templates
Platform: UNKNOWN
Classifier: Development Status :: 3 - Alpha
Classifier: Intended Audience :: Developers
Classifier: Topic :: Software Development :: Build Tools
Classifier: License :: OSI Approved :: Apache Software License
Classifier: Programming Language :: Python :: 3
Classifier: Programming Language :: Python :: 3.5
Classifier: Programming Language :: Python :: 3.6
Requires-Python: >=3
